artemis/artemis.db
artemis/artemis.py
artemis_cli-1.0.1.dist-info/LICENSE
artemis_cli-1.0.1.dist-info/METADATA
artemis_cli-1.0.1.dist-info/WHEEL
artemis_cli-1.0.1.dist-info/entry_points.txt
artemis_cli-1.0.1.dist-info/top_level.txt
artemis_cli-1.0.1.dist-info/RECORD
