Metadata-Version: 2.2
Name: artemis-cli
Version: 1.0.1
Summary: Artemis is a versatile command-line tool designed to interact with Microsoft Azure and Microsoft Entra ID.
Author-email: Tommaso Maria Ungetti <tommaso.ungetti@outlook.com>
License: GPL
License-File: LICENSE
Requires-Dist: click
Requires-Dist: azure-identity
Requires-Dist: requests
Requires-Dist: setuptools
Requires-Dist: colorama
